[
    {
        "Пряная дыня с глинтвейном": {
            "Steps": [
                "Налейте вино в кастрюлю.",
                "Добавьте специи и ягоды.",
                "Насыпьте сахар. Прогрейте вино со специями и сахаром в течение 5-10 минут.",
                "Дыню нарежьте ломтиками, удалите семечки. Счищать кожуру не нужно.",
                "Положите ломтики дыни в горячее вино со специями.",
                "Добавьте веточку мяты и томите дыню в вине на среднем огне в течение 40-50 минут, чтобы уварилось вино. Подавайте, украсив звёздочками бадьяна."
            ],
            "Ingredients": {
                "дыня плотная": "1 шт. (примерно 500 г)",
                "вино красное": "500 мл",
                "сахар": "50 г",
                "корица": "1 палочка",
                "бадьян (звёздочки)": "4-5 шт.",
                "гвоздика": "3-4 шт.",
                "смородина чёрная": "несколько ягод",
                "мята": "веточка"
            }
        }
    },
    {
        "Дынный чизкейк без выпечки в дыне": {
            "Steps": [
                "Печенье поломайте на кусочки и сложите в чашу комбайна или блендера. Измельчите в крошку.",
                "У дыни срежьте крышечку. Аккуратно, не повреждая оболочку, достаньте семечки и мякоть. Мякоть желательно доставать аккуратно — так, чтобы получились кусочки, а не каша. У вас должен остаться «горшочек» из дыни.",
                "Желатин залейте водой согласно инструкции на упаковке, размешайте и оставьте до набухания.",
                "Сделайте крем. Сливки выложите в миску. Добавьте сахар и смешайте до однородности. Добавьте кремчиз и желатин. Перемешайте всё вместе до однородности.",
                "Листья мяты промойте и обсушите, стебли удалите. Сложите мяту в чашу блендера. Выжмите туда сок лаймов и измельчите до однородности.",
                "Выложите в подготовленный ранее «горшочек» из дыни слой крема. Затем — слой измельчённого печенья.",
                "Затем снова слой крема и часть нарезанной кусочками мякоти дыни.",
                "Снова слой крема и слой измельчённой мяты с лаймом. Повторите все слои.",
                "Накройте дыню крышечкой и уберите в холодильник до застывания на 6 часов минимум. Подавайте готовый чизкейк в дыне."
            ],
            "Ingredients": {
                "дыня небольшая": "1,2 кг",
                "кремчиз": "1 банка (200 г)",
                "сливки 38%": "250 г",
                "сахар": "50 г",
                "печенье Савоярди": "6 палочек",
                "желатин": "1 ст. л.",
                "мята": "пучок",
                "лайм": "2 шт."
            }
        }
    },
    {
        "Печенье с черникой и белым шоколадом": {
            "Steps": [
                "Взбейте размягчённое сливочное масло с сахаром до пышности в течение 4 минут.",
                "Замороженную чернику подогрейте в микроволновой печи или на плите до кипения. Остудите и добавьте к маслу, перемешайте до однородности.",
                "Добавьте сухие ингредиенты, вымесите. Нарубите белый шоколад, вмешайте в тесто.",
                "Сформируйте печенье и выпекайте в разогретой до 170 ℃ духовке 10 минут."
            ],
            "Ingredients": {
                "мука": "180 г",
                "разрыхлитель": "2 г",
                "сахар": "80 г",
                "сливочное масло 82,5%": "80 г",
                "черника замороженная": "80 г",
                "белый шоколад": "60 г",
                "соль": "щепотка"
            }
        }
    },
    {
        "Десертный дынный суп": {
            "Steps": [
                "Почистите дыню, удалите семечки. Мякоть нарежьте крупно и положите в чашу кухонного комбайна или блендера.",
                "Добавьте к дыне сахар.",
                "Налейте вино.",
                "Выжмите сок лимона.",
                "Измельчите всё вместе до однородности. Листья базилика можете добавить в суп, измельчив вместе с остальными ингредиентами, или же украсить ими при подаче. Также при подаче можете добавить лёд."
            ],
            "Ingredients": {
                "дыня": "500 г",
                "сахар": "30 г",
                "белое вино": "50 мл",
                "базилик": "2 веточки",
                "лимон сок": "1 ст. л.",
                "лёд": "для подачи (по желанию)"
            }
        }
    },
    {
        "Тефтели с рисом и подливкой": {
            "Steps": [
                "Сделайте подливу. Лук и чеснок почистите и нарежьте крупно. Стебли сельдерея нарежьте ломтиками толщиной примерно 1-2 см. Положите всё в чашу или стакан блендера.",
                "Морковь почистите, нарежьте шайбами толщиной примерно 1 см, а затем четвертинками.",
                "Положите к остальным овощам. Добавьте томаты и 200 мл воды.",
                "Измельчите всё вместе блендером до однородности.",
                "Переложите получившуюся подливу в сотейник или кастрюлю. Добавьте ¼ ч. л. соли, ¼ ч. л. чёрного молотого перца, перемешайте и тушите примерно 10 минут. Крышкой накрывать не нужно.",
                "Отварите 70 г риса до готовности. Вам понадобится 180 г варёного риса.",
                "Мясо очистите от жил, если есть, и нарежьте крупными кубиками. Одну луковицу также нарежьте крупно.",
                "Прокрутите мясо с луком через мясорубку.",
                "Добавьте варёный рис, молоко и яйцо. Насыпьте панировочные сухари.",
                "Хорошо вымесите фарш руками и сформуйте тефтели диаметром примерно 5-6 см.",
                "Выложите тефтели в подготовленный ранее соус. Налейте ряженку. Накройте крышкой и тушите примерно 20-30 минут. Через 10 минут после начала тушения аккуратно перемешайте. Готовые тефтели подавайте с подливкой."
            ],
            "Ingredients": {
                "говядина, лопатка": "300 г",
                "свинина, окорок": "300 г",
                "рис басмати": "70 г",
                "лук репчатый": "1 шт.",
                "сухари панировочные": "1 ст. л. (15-20 г)",
                "яйцо": "1 шт.",
                "молоко": "120 мл",
                "перец чёрный молотый": "1/4 ч. л.",
                "соль": "1/4 ч. л.",
                "томаты консервированные, нарезанные кубиками": "1 банка (240 г)",
                "ряженка": "150 г",
                "морковь среднего размера": "1 шт.",
                "лук маленький": "3 шт.",
                "чеснок": "2 зуб.",
                "сельдерей, стебли": "3 шт.",
                "вода": "200 мл"
            }
        }
    },
    {
        "Цукаты морковные": {
            "Steps": [
                "Морковь почистите и нарежьте соломкой.",
                "Насыпьте сахар в кастрюлю.",
                "Налейте воду или апельсиновый сок.",
                "Добавьте гвоздику.",
                "Нагревайте всё вместе до полного растворения сахара в течение 5 минут.",
                "Добавьте нарезанную морковь, доведите до кипения и оставьте на 30 минут.",
                "Ещё раз доведите до кипения и варите 1 минуту. Оставьте на 1 час. Повторите 3 раза.",
                "Достаньте ломтики моркови из сиропа, разложите на пергаменте и оставьте до высыхания при комнатной температуре. По желанию обсыпьте цукаты сахаром. Оставшийся сироп можно использовать для приготовления следующей порции цукатов из моркови."
            ],
            "Ingredients": {
                "морковь": "300 г",
                "сахар": "500 г + для обсыпки (по желанию)",
                "вода или апельсиновый сок": "50 мл",
                "гвоздика": "3 шт."
            }
        }
    },
    {
        "Варенье из помидоров": {
            "Steps": [
                "Помидоры помойте, удалите зелёные хвостики, если есть. В небольшую кастрюлю насыпьте сахар.",
                "У лимона удалите косточки и выжмите сок в кастрюлю с сахаром.",
                "Положите специи. Поставьте на огонь и нагревайте до растворения сахара. Перемешайте и доведите до кипения.",
                "Добавьте помидоры. Доведите всё вместе до кипения и снимите с плиты. Оставьте на 30 минут. Затем ещё раз доведите до кипения и оставьте на час.",
                "Спустя час ещё раз доведите до кипения и положите в чистую сухую банку. Храните в холодильнике до 1 месяца."
            ],
            "Ingredients": {
                "помидоры черри": "500 г",
                "сахар": "300 г",
                "лимон": "1 шт. (только сок)",
                "перец душистый горошком": "3 шт.",
                "бадьян": "1 шт."
            }
        }
    },
    {
        "Торт с гранатовым желе с шариками из дыни": {
            "Steps": [
                "Дыню разрежьте пополам, удалите семена. Часть почистите и нарежьте небольшими кусочками — вам понадобится 500 г мякоти. Высыпьте желатин в ковш, налейте 125 мл воды и прогрейте до кипения, помешивая.",
                "Положите нарезанную дыню в чашу кухонного комбайна или блендера, добавьте сок половины лайма и измельчите до однородности. Если дыня не очень сладкая, можно добавить в дынное пюре 40 г сахара.",
                "Добавьте 70 г желатиновой массы в дынное пюре, перемешайте до однородности и вылейте в форму для торта.",
                "Удобнее всего использовать силиконовую или разъёмную форму, но можно и обычную, если из неё можно будет легко достать застывший торт. Уберите в морозилку на полчаса.",
                "В оставшуюся желатиновую массу вылейте гранатовый сок, перемешайте. Если желатин успел схватиться, поставьте смесь на медленный огонь и нагревайте, помешивая, до тех пор, пока не получится однородная смесь. Оставьте при комнатной температуре.",
                "Сделайте из дыни шарики специальной ложкой (нуазеткой).",
                "Когда дынный слой схватится, залейте его гранатовым соком с желатином.",
                "Добавьте часть дынных шариков, часть оставьте для украшения. Уберите в холодильник минимум на 2 часа до полного застывания.",
                "Готовый торт аккуратно достаньте из формы. Украсьте оставшимися шариками из дыни, свежей мятой и свежими ягодами и подавайте."
            ],
            "Ingredients": {
                "гранатовый сок": "500 мл",
                "дыня": "500 г для желе + 100-200 г для шариков",
                "желатин": "3 пачки (45 г)",
                "вода": "125 мл",
                "лайм": "1/2 шт.",
                "сахар": "40 г (по желанию)",
                "голубика или черника": "для украшения",
                "мята": "для украшения"
            }
        }
    },
    {
        "Варенье из дыни": {
            "Steps": [
                "Насыпьте сахар в кастрюлю.",
                "Выжмите туда же сок лимона.",
                "Поставьте на огонь и прогревайте до полного растворения сахара, должны образовываться крупные пузыри.",
                "Дыню очистите от кожуры и семечек.",
                "Нарежьте кусочками среднего размера.",
                "Положите дыню в кастрюлю с сахарным сиропом и готовьте 5 минут. Готовое варенье остудите и храните в холодильнике в банке до 1 месяца. Если варить его в 3 приёма, каждый раз доводя до кипения, проваривая 5 минут и остужая, то в конце такое варенье из дыни можно закатать в банки и хранить в тёмном прохладном месте. Однако тогда сахар стоит взять в пропорции 1:1 с дыней."
            ],
            "Ingredients": {
                "дыня": "800 г",
                "сахар": "400 г",
                "лимон": "1 шт."
            }
        }
    },
    {
        "Веер из баклажанов в духовке": {
            "Steps": [
                "Баклажаны нарезаем веером, солим и даем постоять минут 40, чтобы горечь ушла.",
                "За это время тонко нарезаем сыр и помидоры.",
                "Моем и обсушиваем баклажаны, между каждой пластинки кладём сыр и помидоры. Затем выкладываем веер на противень. Не солим!",
                "Сверху веер мажем сметаной или майонезом или любым соусом на их основе ( по вкусу).",
                "Запекаем при температуре 200-220 ℃ от 30 до 50 минут.",
                "Баклажаны готовы, когда  становятся мягкими и слегка румяными."
            ],
            "Ingredients": {
                "баклажаны": "4 шт.",
                "помидоры": "4 шт.",
                "сыр твёрдый/полутвёрдый": "200 г",
                "сметана": "по вкусу",
                "соль": "по вкусу"
            }
        }
    },
    {
        "Тёплый салат с грибами эноки": {
            "Steps": [
                "Баклажаны нарезать брусочками и обжарить.",
                "Морковь нарезать брусочками или натереть на тёрке для корейской морковки и обжарить вместе с баклажаном.",
                "Эноки промыть и добавить к овощам, обжарить ещё 2 минуты. В последнюю минуту добавить в сковороду чили и соевый соус.",
                "Шпинат промыть и обсушить, положить на тарелку. Добавить обжаренные овощи и грибы и подавать салат в тёплом виде, посыпав кунжутом."
            ],
            "Ingredients": {
                "эноки": "150 г",
                "баклажан": "100 г",
                "морковь": "100 г",
                "шпинат мелкий": "по вкусу",
                "соевый соус": "по вкусу",
                "соус чили": "по вкусу",
                "кунжут": "по вкусу"
            }
        }
    },
    {
        "Пирожки в вафельнице из зелёной гречки и курицы": {
            "Steps": [
                "Замочите зелёную гречку в теплой воде на 40 минут или оставьте на ночь.",
                "Промойте гречку проточной водой, переложите в блендер. Добавьте яйцо и пробейте до однородной консистенции. Можно добавить немного воды, чтобы масса было более жидкой.",
                "Филе нарежьте на мелкие кусочки.",
                "Соедините мясо и жидкую смесь из гречки и яйца. Добавьте специи. Хорошо перемешайте.",
                "Выпекайте на хорошо разогретой сковороде.",
                "Вафли готовы."
            ],
            "Ingredients": {
                "зелёная гречка": "80 г",
                "куриное филе": "110 г",
                "яйцо куриное": "1 шт.",
                "итальянские травы": "по вкусу",
                "соль": "по вкусу"
            }
        }
    },
    {
        "Мясной хлеб в духовке": {
            "Steps": [
                "Смешайте все ингредиенты в чаше блендера.",
                "Взбейте в блендере до однородной воздушной консистенции. Это займёт около 5 минут.",
                "Переложите тесто в форму для выпечки, разровняйте. Готовьте в разогретой до 180 ℃ духовке 35 минут.",
                "Нарежьте на порционные куски и подавайте с любимым соусом."
            ],
            "Ingredients": {
                "фарш из свинины и говядины": "360 г",
                "сало": "100 г",
                "лёд": "100 г",
                "разрыхлитель": "3 г",
                "перец": "щепотка",
                "соль": "щепотка",
                "мускатный орех": "щепотка",
                "паприка": "щепотка",
                "сушёный чеснок": "щепотка"
            }
        }
    },
    {
        "Варенье из кабачков с апельсином": {
            "Steps": [
                "Кабачки помойте, удалите плодоножки и нарежьте кубиками. Для варенья лучше брать молодые кабачки с тонкой кожицей и маленькими мягкими семечками — у таких ни кожицу срезать не нужно, ни семечки удалять.",
                "Сложите нарезанные кабачки в большую миску. Апельсин помойте и разрежьте пополам. Из одной половины выжмите сок в кабачки.",
                "Вторую половину нарежьте ломтиками и добавьте в миску с кабачками.",
                "Засыпьте кабачки с апельсином сахаром и оставьте на несколько часов, пока не выделится сок.",
                "Переложите всё в кастрюлю, перемешайте и поставьте на плиту. Доведите до кипения и варите 3-4 минуты.",
                "Снимите кастрюлю с огня, по желанию достаньте апельсины, если опасаетесь, что кожура будет горчить. Оставьте на 5-6 часов, накрыв тонким полотенцем. Повторите всё ещё 2 раза.",
                "Прокипятив варенье в третий раз, разлейте его по сухим стерилизованным банкам, закройте крышками. Укутайте банки чем-то тёплым и оставьте до полного остывания. Уберите на хранение в холод."
            ],
            "Ingredients": {
                "кабачки": "3 шт. (500 г)",
                "апельсин": "1 шт.",
                "сахар": "500 г"
            }
        }
    },
    {
        "Желе из красной смородины": {
            "Steps": [
                "Смешайте ягоды с сахаром, проварите на среднем огне до полного растворения сахара. Это займёт около 6 минут.",
                "Замочите желатин на 10 минут и оставьте набухать.",
                "Затем набухший желатин добавьте в горячую, но не кипящую смесь. Перемешайте.",
                "Наполните порционные стаканчики и уберите в холодильник минимум на 2 часа."
            ],
            "Ingredients": {
                "красная смородина": "600 г",
                "сахар": "200 г",
                "желатин": "15 г",
                "вода": "90 г"
            }
        }
    },
    {
        "Огуречный сорбет": {
            "Steps": [
                "Огурцы нарежьте крупными шайбами. Для этого рецепта выбирайте сезонные молодые огурчики. Если кожица у огурцов плотная и жестковатая, лучше срежьте её. Если тонкая, лучше оставьте — так цвет сорбета получится ярче и насыщеннее.",
                "Положите огурцы в чашу кухонного комбайна или блендера, выжмите туда же сок целого лайма.",
                "Насыпьте сахар.",
                "Добавьте базилик.",
                "Измельчите всё вместе на высокой скорости до полной однородности.",
                "Вылейте получившуюся смесь в плоское блюдо и уберите в морозилку. Сорбет застынет в течение примерно 2 часов.",
                "Ложкой для мороженого сделайте шарики. При подаче украсьте базиликом, ломтиком лайма и по желанию ломтиками или палочками огурца."
            ],
            "Ingredients": {
                "огурцы трилоджи": "8 шт.",
                "сахар": "100 г",
                "лайм": "1 шт.",
                "базилик зелёный": "несколько веточек"
            }
        }
    },
    {
        "Алсу — татарский кисломолочный напиток ": {
            "Steps": [
                "Свёклу вымыть, очистить от кожуры и нарезать тонкими ломтиками.",
                "Молоко влить в стеклянную или керамическую посуду и добавить мёд, тщательно размешать до полного растворения.",
                "Влить в смесь катык.",
                "Добавить свёклу.",
                "Оставить посуду со смесью на 10–12 часов в тёплом месте.",
                "Процедить, охладить и разлить по стаканам."
            ],
            "Ingredients": {
                "пастеризованное молоко": "1 л",
                "катык для сквашивания": "350 г (одна банка)",
                "свёкла": "1 шт.",
                "жидкий мёд": "3 ст. л."
            }
        }
    },
    {
        "Губадия — татарский праздничный пирог": {
            "Steps": [
                "Для теста охлаждённое масло натереть на крупной тёрке, добавить соль и три стакана муки. Перетереть руками до состояния крошки.",
                "Положить в кефир разрыхлитель и перемешать.",
                "Влить кефир в мучную смесь и замесить тесто. При необходимости подсыпать ещё муки. Тесто должно быть мягким, но не липким. Накрыть его салфеткой и оставить на 20 минут.",
                "Для корта. Творог выложить в толстостенную посуду, залить ряженкой, добавить сахар. Томить на медленном огне около одного часа до получения однородной консистенции цвета топлёного молока и охладить.",
                "Отварить рис в подсоленной воде до готовности.",
                "Нарезать кубиками яйца.",
                "Промыть изюм и залить горячей водой на 20 минут.",
                "Обжарить мелко нарезанный лук вместе с фаршем, добавить соль и перец. Охладить.",
                "Разделить тесто на 2 части (2/3 для нижней части пирога, 1/3 для крышечки). Раскатать большую часть теста и выложить в толстостенную форму для выпекания, смазанную маслом.",
                "Выложить начинку в такой последовательности: 1/3 риса — корт — 1/3 риса — фарш — яйца — 1/3 риса — изюм.",
                "Растопить сливочное масло и полить начинку.",
                "Раскатать оставшееся тесто и накрыть пирог, защипав края.",
                "Смазать поверхность взбитым сырым яйцом, проткнуть в нескольких местах вилкой или зубочисткой и отправить в духовку. Выпекать около 50 минут при температуре 180 градусов."
            ],
            "Ingredients": {
                "яйца, сваренные вкрутую": "6 шт.",
                "сырое яйцо": "1 шт.",
                "сливочное масло": "300 г в начинку + 300 г в тесто + для смазывания формы",
                "рис": "1,5 стакана",
                "изюм": "150 г",
                "говяжий фарш": "800 г",
                "луковица": "1 шт.",
                "соль": "1,5 чайные ложки + по вкусу в начинку",
                "перец": "по вкусу",
                "ряженка": "0,5 стакана",
                "рассыпчатый творог": "300 г",
                "сахара": "2 ст. л.",
                "мука": "4 стакана",
                "кефир": "300 мл",
                "разрыхлитель": "3 ч. л."
            }
        }
    },
    {
        "Закуска-намазка из томатов с сыром": {
            "Steps": [
                "Нарежьте багет длинными ломтиками и подсушите на сухой сковороде.",
                "Твёрдый сыр натрите на мелкой тёрке. Чеснок почистите и нарежьте произвольно.",
                "У помидора удалите плодоножку, мякоть нарежьте произвольно. Сложите в чашу блендера. Добавьте тёртый сыр, чеснок, немного перца чили по желанию и оливковое масло.",
                "Измельчите всё блендером. При необходимости посолите по вкусу, если солёности сыра не хватает. Подавайте с подсушенными ломтиками багета."
            ],
            "Ingredients": {
                "багет": "несколько ломтиков",
                "твёрдый сыр": "100-150 г",
                "чеснок": "1-2 зуб.",
                "крупный помидор": "1 шт.",
                "масло оливковое": "1 ч. л.",
                "перец чили": "по вкусу и по желанию",
                "соль": "по вкусу"
            }
        }
    },
    {
        "Туррон": {
            "Steps": [
                "В ковш налейте мёд, добавьте 1 столовую ложку сахарного песка и поставьте на огонь. Перемешайте и прогревайте, помешивая при необходимости, примерно 5 минут на сред-нем огне, пока мёд не станет очень жидким. При этом мёд не должен кипеть и подниматься, должны быть маленькие пузырьки.",
                "Смажьте растительным маслом круглую или прямоугольную силиконовую форму для вы-печки.",
                "Орехи обжарьте на сухой сковороде или запеките в духовке.",
                "В чашу миксера налейте белок крупного куриного яйца.",
                "Добавьте сахарную пудру и взбейте до твёрдых пиков.",
                "Продолжая взбивать, влейте тонкой струйкой нагретый мёд и взбейте всё вместе до очень твёрдых пиков.",
                "Порциями добавьте орехи и перемешайте.",
                "Выложите смесь в силиконовую форму, разровняйте поверхность лопаткой. Уберите в холодильник на 2-3 часа или дольше до застывания. Готовый туррон нарежьте и подавай-те."
            ],
            "Ingredients": {
                "орехи": "150 г",
                "мёд": "260 г",
                "сахар": "1 ст. л.",
                "белок крупного яйца": "1 шт.",
                "сахарная пудра": "100 г",
                "растительное масло": "1 ч. л."
            }
        }
    },
    {
        "Батат фри с соусом из пломбира": {
            "Steps": [
                "Батат очистите от кожуры. Нарежьте соломкой толщиной примерно 0,5-1 см и выложите в миску.",
                "Добавьте 2-2,5 ч. л. соли, перемешайте.",
                "Добавьте крахмал и снова перемешайте.",
                "Застелите противень пергаментом для выпечки. Выложите подготовленный батат, смажьте его маслом. Запекайте в разогретой до 200 ℃ духовке в течение 20 минут. По желанию предварительно отварите батат в подсоленной воде (1 л) на сильном огне в течение 4-5 минут. Обсушите на бумажном полотенце и остудите, затем об-валяйте в кукурузном крахмале, выложите на противень и далее готовьте по рецепту. Это особенно пригодится, если захотите нарезать батат более толстыми ломтиками, чтобы они при запекании стали посуше.",
                "Пока запекается батат, сделайте соус. Мелко нарежьте перец чили, убрав из него семена, и выложите в мисочку.",
                "Отделите листья мяты от стеблей, мелко нарежьте и добавьте к перцу чили.",
                "Налейте бальзамический соус. Посолите. Перемешайте.",
                "Добавьте немного подтаявшее мороженое и смешайте до соединения компонентов. Если после запекания батат немного влажный, выложите его на бумажное полотенце. Подавайте с соусом, по желанию посыпав тёртым пармезаном. Также можете добавить 1-2 шарика мороженого."
            ],
            "Ingredients": {
                "батат": "3-4 шт.",
                "крахмал кукурузный": "1 ст. л. с горкой (20 г)",
                "соль": "3,5 ч. л. (15 г)",
                "масло растительное": "30 мл",
                "пломбир": "150 г",
                "перец чили свежий (или молотый сухой)": "1 шт. (1/3 ч. л.)",
                "бальзамический соус": "20 мл",
                "мята или базилик": "1 веточка"
            }
        }
    },
    {
        "Цыплёнок-корнишон в красном вине": {
            "Steps": [
                "Лук, морковь и чеснок почистите. Лук нарежьте кубиками среднего размера, морковь – кружочками, чеснок — ломтиками.",
                "Разогрейте кастрюлю с оливковым маслом. Выложите в неё подготовленные овощи и обжарьте в течение нескольких минут, помешивая при необходимости.",
                "У перца удалите плодоножку и семена, мякоть нарежьте полосками и положите к остальным овощам.",
                "Цыплёнка нарежьте на части.",
                "Добавьте к овощам красное вино, соль, сахар, перемешайте и доведите до кипения.",
                "Положите нарезанного цыплёнка, несколько веточек тимьяна и тушите 1 час под крышкой."
            ],
            "Ingredients": {
                "цыплёнок-корнишон": "1 шт.",
                "вино красное": "300 мл",
                "лук репчатый": "1 шт.",
                "чеснок": "2 зуб.",
                "морковь": "1 шт.",
                "болгарский перец": "1 шт.",
                "масло оливковое": "1 ст. л.",
                "соль": "1 ч. л. или по вкусу",
                "сахар": "1 ч. л.",
                "тимьян": "несколько веточек (по желанию)"
            }
        }
    },
    {
        "Чуррос": {
            "Steps": [
                "В миску насыпьте муку, молотую корицу, разрыхлитель и соль. Перемешайте.",
                "Налейте в ковш 200 воды и доведите до кипения. Добавьте сливочное масло, сахар и всё вместе до кипения.",
                "Высыпьте сухие ингредиенты в жидкие, верните на огонь и нагревайте, интенсивно мешая, пока тесто не станет однородным и на дне кастрюли не образуется плёнка.",
                "Добавьте одно яйцо, интенсивно перемешайте. Добавьте второе яйцо и снова интенсивно перемешайте лопаткой или миксером с насадкой-крюком до однородности. Тесто должно получиться достаточно густым. Если оно слишком густое, добавьте ещё немного горячей воды и перемешайте. Если яйца очень мелкие, можете добавить ещё одно яйцо.",
                "Хорошо разогрейте в ковше растительное масло для жарки. Проверить температуру можно так: аккуратно положите в масло маленький кусочек теста — если пошли пузырьки и тесто начало жариться, фритюр достаточно разогрелся. Вставьте в кулинарный мешок насадку для теста с наконечником в форме звезды (такие мешки и насадки легко можно купить на маркетплейсах).",
                "Выдавливайте во фритюр тесто небольшими полосками и обжаривайте до румяности в течение 3-5 минут.",
                "Готовые полоски теста выложите на бумажные полотенца, чтобы убрать лишний жир. Подавайте чуррос, украсив сахарной пудрой или с любимым шоколадным соусом."
            ],
            "Ingredients": {
                "мука пшеничная": "160 г",
                "вода": "200 мл",
                "корица молотая": "1/2 ч. л.",
                "разрыхлитель": "1 ст. л. (10 г)",
                "масло сливочное": "60 г",
                "яйца С1": "2 шт.",
                "сахар": "1 ст. л.",
                "соль": "1/4 ч. л.",
                "сахарная пудра для подачи": "1 ст. л.",
                "масло подсолнечное (для жарки)": "500 мл"
            }
        }
    },
    {
        "Брускетта с томатами и хамоном": {
            "Steps": [
                "Багет нарежьте наискосок длинными ломтиками и подсушите на сухой сковороде.",
                "У томатов удалите плодоножку и нарежьте мякоть кубиками.",
                "У зубчиков чеснока по желанию удалите сердцевинки и пропустите чеснок через пресс или мелко нарежьте.",
                "Листья базилика помойте, обсушите и нарежьте. Сложите в миску томаты, чеснок и базилик, перемешайте.",
                "Добавьте соль и оливковое масло. Перемешайте.",
                "Выложите на подсушенные ломтики хлеба томаты с чесноком и зеленью.",
                "Сверху — ломтики хамона. Подавайте, украсив листьями базилика."
            ],
            "Ingredients": {
                "багет": "3-6 ломтиков",
                "хамон": "1 упаковка (70 г)",
                "оливковое масло": "1 ч. л. или по вкусу",
                "соль": "по вкусу",
                "томаты свежие": "2 шт.",
                "чеснок": "2 зуб.",
                "базилик зелёный": "несколько листьев по вкусу"
            }
        }
    }
]